SigProfilerTopography/Topography.py
SigProfilerTopography/__init__.py
SigProfilerTopography/version.py
SigProfilerTopography/lib/md5.txt
SigProfilerTopography/lib/epigenomics/ENCFF061UVF_GRCh38_upper-lobe-of-left-lung_CTCF.bed
SigProfilerTopography/lib/epigenomics/ENCFF065FJK_breast_epithelium_H3K9me3.bed
SigProfilerTopography/lib/epigenomics/ENCFF065TIH_breast_epithelium_H3K4me3.bed
SigProfilerTopography/lib/epigenomics/ENCFF069GQK_GRCh38_lung_H3K4me3-human.bed
SigProfilerTopography/lib/epigenomics/ENCFF078AMJ_GRCh38_upper-lobe-of-left-lung_H3K36me3-human.bed
SigProfilerTopography/lib/epigenomics/ENCFF114VLZ_mm10_embryonic_fibroblast_H3K27ac.bed
SigProfilerTopography/lib/epigenomics/ENCFF152DUV_mm10_embryonic_fibroblast_POLR2A.bed
SigProfilerTopography/lib/epigenomics/ENCFF154XFN_breast_epithelium_H3K27ac.bed
SigProfilerTopography/lib/epigenomics/ENCFF185EKW_GRCh38_left-lung_H3K9me3-human.bed
SigProfilerTopography/lib/epigenomics/ENCFF291WFP_breast_epithelium_H3K27me3.bed
SigProfilerTopography/lib/epigenomics/ENCFF336DDM_breast_epithelium_H3K4me1.bed
SigProfilerTopography/lib/epigenomics/ENCFF367LMT_GRCh38_lower-lobe-of-left-lung_H3K27me3-human.bed
SigProfilerTopography/lib/epigenomics/ENCFF611HDQ_mm10_embryonic_fibroblast_CTCF.bed
SigProfilerTopography/lib/epigenomics/ENCFF782GCQ_breast_epithelium_Normal_CTCF-human.bed
SigProfilerTopography/lib/epigenomics/ENCFF846LAZ_GRCh38_left-lung_H3K27ac-human.bed
SigProfilerTopography/lib/epigenomics/ENCFF906MJM_breast_epithelium_H3K36me3.bed
SigProfilerTopography/lib/epigenomics/ENCFF908EUN_GRCh38_lung_H3K4me1-human.bed
SigProfilerTopography/lib/epigenomics/ENCFF912DNP_mm10_embryonic_fibroblast_H3K4me3.bed
SigProfilerTopography/lib/epigenomics/ENCFF993SRY_mm10_embryonic_fibroblast_H3K4me1.bed
SigProfilerTopography/lib/replication/ENCFF001JVQ_mm10_embryonic_fibroblast_wavelet_smoothed_signal.wig
SigProfilerTopography/lib/replication/GSM923442_hg19_wgEncodeUwRepliSeqMcf7PkRep1.bed
sigprofilertopography-1.0.107.dist-info/licenses/LICENSE.txt
sigprofilertopography-1.0.107.dist-info/METADATA
sigprofilertopography-1.0.107.dist-info/WHEEL
sigprofilertopography-1.0.107.dist-info/top_level.txt
sigprofilertopography-1.0.107.dist-info/RECORD
