Metadata-Version: 2.4
Name: SigProfilerTopography
Version: 1.0.107
Summary: SigProfilerTopography provides topography analyses for substitutions, dinucleotides and indels for all given samples.
Home-page: https://github.com/AlexandrovLab/SigProfilerTopography
Author: Burcak Otlu
Author-email: burcakotlu@eng.ucsd.edu
License: UCSD
Requires-Python: >=3.9
License-File: LICENSE.txt
Requires-Dist: SigProfilerMatrixGenerator>=1.1.27
Requires-Dist: SigProfilerSimulator>=1.1.2
Requires-Dist: SigProfilerAssignment>=0.1.0
Requires-Dist: XlsxWriter>=1.3.7
Requires-Dist: numpy>=2.0.0
Requires-Dist: pandas>=2.0.0
Requires-Dist: matplotlib>=3.4.3
Requires-Dist: scipy>=1.1.0
Requires-Dist: statsmodels>=0.9.0
Requires-Dist: fastrand>=1.2
Requires-Dist: psutil>=5.6.3
Requires-Dist: pyranges>=0.1.1
Requires-Dist: intervaltree>=3.1.0
Dynamic: author
Dynamic: author-email
Dynamic: home-page
Dynamic: license
Dynamic: license-file
Dynamic: requires-dist
Dynamic: requires-python
Dynamic: summary
